AUTHORS.rst
CONTRIBUTING.rst
HISTORY.rst
LICENSE
MANIFEST.in
README.rst
setup.cfg
setup.py
docs/Makefile
docs/authors.rst
docs/conf.py
docs/contributing.rst
docs/history.rst
docs/index.rst
docs/installation.rst
docs/make.bat
docs/readme.rst
docs/usage.rst
romans/__init__.py
romans.egg-info/PKG-INFO
romans.egg-info/SOURCES.txt
romans.egg-info/dependency_links.txt
romans.egg-info/not-zip-safe
romans.egg-info/top_level.txt
tests/__init__.py
tests/test_romans.py