Metadata-Version: 1.1
Name: romans
Version: 0.1.0
Summary: Roman Numeral Converter converts Roman numerals.
Home-page: https://github.com/drincruz/romans
Author: Adrian Cruz
Author-email: drincruz@gmail.com
License: BSD
Keywords: romans
Platform: UNKNOWN
Classifier: Development Status :: 2 - Pre-Alpha
Classifier: Intended Audience :: Developers
Classifier: License :: OSI Approved :: BSD License
Classifier: Natural Language :: English
Classifier: Programming Language :: Python :: 2
Classifier: Programming Language :: Python :: 2.6
Classifier: Programming Language :: Python :: 2.7
Classifier: Programming Language :: Python :: 3
Classifier: Programming Language :: Python :: 3.3
Classifier: Programming Language :: Python :: 3.4
